{"cameraMode":{"drawMode":0,"name":"Shaded","section":"Shading Mode"},"sceneLighting":false,"audioPlay":false,"sceneViewState":{"m_AlwaysRefresh":false,"showFog":true,"showSkybox":false,"showFlares":true,"showImageEffects":true,"showParticleSystems":true,"showVisualEffectGraphs":true,"m_FxEnabled":true},"in2DMode":false,"pivot":{"x":-1.5206384658813477,"y":0.8762892484664917,"z":0.6069289445877075},"rotation":{"x":0.07015077769756317,"y":-0.815177321434021,"z":0.10103323310613632,"w":0.566012978553772},"size":2.598076105117798,"orthographic":false}