{"cameraMode":{"drawMode":0,"name":"Shaded","section":"Shading Mode"},"sceneLighting":true,"audioPlay":false,"sceneViewState":{"m_AlwaysRefresh":false,"showFog":true,"showSkybox":true,"showFlares":true,"showImageEffects":true,"showParticleSystems":true,"showVisualEffectGraphs":true,"m_FxEnabled":true},"in2DMode":false,"pivot":{"x":822.836181640625,"y":806.4082641601563,"z":-796.5484619140625},"rotation":{"x":-0.0017856808844953776,"y":0.16305068135261537,"z":-0.0002957838587462902,"w":-0.9866172671318054},"size":1.2247449159622193,"orthographic":false}